listfs/__init__.py
listfs/main.py
listfs-0.6.1.dist-info/METADATA
listfs-0.6.1.dist-info/WHEEL
listfs-0.6.1.dist-info/entry_points.txt
listfs-0.6.1.dist-info/licenses/LICENSE
listfs-0.6.1.dist-info/RECORD
