Metadata-Version: 2.4
Name: listfs
Version: 0.6.1
Summary: Mount file listings as a FUSE filesystem
Project-URL: homepage, https://github.com/d10n/listfs-py
Project-URL: issues, https://github.com/d10n/listfs-py/issues
Project-URL: source, https://github.com/d10n/listfs-py.git
Author-email: d10n <david@bitinvert.com>
License-Expression: GPL-3.0-or-later
License-File: LICENSE
Keywords: backup,fuse,lto,tape
Classifier: Development Status :: 4 - Beta
Classifier: Environment :: Console
Classifier: Intended Audience :: System Administrators
Classifier: License :: OSI Approved :: GNU General Public License v3 or later (GPLv3+)
Classifier: Operating System :: POSIX :: Linux
Classifier: Programming Language :: Python :: 3
Classifier: Programming Language :: Python :: 3.12
Classifier: Topic :: System :: Archiving :: Backup
Classifier: Topic :: System :: Systems Administration
Classifier: Topic :: Utilities
Requires-Python: >=3.12
Requires-Dist: lz4>=4.4.3
Requires-Dist: pyfuse3>=3.4.0
Requires-Dist: trio>=0.28.0
Requires-Dist: zstandard>=0.23.0
